lydlab.py
lyload.py
lydlab-0.0.2.dist-info/METADATA
lydlab-0.0.2.dist-info/WHEEL
lydlab-0.0.2.dist-info/top_level.txt
lydlab-0.0.2.dist-info/RECORD
