Metadata-Version: 2.1
Name: lydlab
Version: 0.0.2
Summary: 数据集下载工具
Home-page: UNKNOWN
Author: zhaomoqiang
License: UNKNOWN
Platform: UNKNOWN
